bootstrap_stat/bootstrap_stat.py
bootstrap_stat/data/hormone_data.csv
bootstrap_stat/data/law_school.csv
bootstrap_stat/data/patch.csv
bootstrap_stat/data/rainfall.csv
bootstrap_stat/data/spatial_test.csv
bootstrap_stat/datasets.py
bootstrap_stat-0.2.4.2.dist-info/LICENSE.txt
bootstrap_stat-0.2.4.2.dist-info/WHEEL
bootstrap_stat-0.2.4.2.dist-info/METADATA
bootstrap_stat-0.2.4.2.dist-info/RECORD
