Metadata-Version: 2.1
Name: bootstrap-stat
Version: 0.2.4.2
Summary: Bootstrap method for standard errors, confidence intervals, and more!
Home-page: https://github.com/rwilson4/bootstrap-stat
License: Apache-2.0
Keywords: statistics,nonparametric,machine learning
Author: Bob Wilson
Author-email: bob@convexanalytics.com
Requires-Python: >=3.6
Classifier: License :: OSI Approved :: Apache Software License
Classifier: Programming Language :: Python :: 3
Classifier: Programming Language :: Python :: 3.6
Classifier: Programming Language :: Python :: 3.7
Classifier: Programming Language :: Python :: 3.8
Requires-Dist: numpy (>=1.17)
Requires-Dist: pandas (>=0.25.1)
Requires-Dist: pathos (>=0.2.5)
Requires-Dist: scipy (>=1.3)
Project-URL: Documentation, https://www.convexanalytics.com/bootstrap-stat/index.html
Project-URL: Repository, https://github.com/rwilson4/bootstrap-stat
